<?xml version = '1.0' encoding = 'UTF-8'?>
<Relation class="oracle.dbtools.crest.model.design.logical.Relation" name="Relation_57" directorySegmentName="seg_0" id="0623B93A-30EB-AB71-62B7-64B185C353F6">
<createdBy>fmarkoja</createdBy>
<createdTime>2018-11-23 14:56:59 UTC</createdTime>
<ownerDesignName>ILF_Datenmodell</ownerDesignName>
<engineerTo>
<item key="2B3881C3-1B43-1B13-52EF-F8AC99A11B8C" value="true"/>
</engineerTo>
<identifying>false</identifying>
<optionalSource>true</optionalSource>
<optionalTarget>false</optionalTarget>
<sourceCardinality>1</sourceCardinality>
<sourceEntity>C8EB9644-121E-DB56-EC83-70CAFD4228B0</sourceEntity>
<targetCardinalityString>*</targetCardinalityString>
<targetEntity>C8EB9644-121E-DB56-EC83-70CAFD4228B0</targetEntity>
<transferable>true</transferable>
<deleteRule>NO ACTION</deleteRule>
</Relation>